{
  "waves": [
    {
      "waveSections": {
        "0": {
          "Location": "South",
          "NumLightEnemies": 0,
          "NumMedEnemies": 1,
          "NumHeavyEnemies": 0
        },
        "100": {
          "Location": "South",
          "NumLightEnemies": 0,
          "NumMedEnemies": 1,
          "NumHeavyEnemies": 0
        },
        "240": {
          "Location": "South",
          "NumLightEnemies": 0,
          "NumMedEnemies": 1,
          "NumHeavyEnemies": 0
        },
        "400": {
          "Location": "South",
          "NumLightEnemies": 0,
          "NumMedEnemies": 1,
          "NumHeavyEnemies": 0
        },
        "500": {
          "Location": "South",
          "NumLightEnemies": 0,
          "NumMedEnemies": 1,
          "NumHeavyEnemies": 0
        }
      }
    }
  ]
}