{
  "waves": [
    {
      "waveSections": {
        "0": {
          "Location": "South",
          "NumLightEnemies": 0,
          "NumMedEnemies": 1,
          "NumHeavyEnemies": 0
        },
        "200": {
          "Location": "West",
          "NumLightEnemies": 2,
          "NumMedEnemies": 0,
          "NumHeavyEnemies": 0
        },
        "240": {
          "Location": "South",
          "NumLightEnemies": 1,
          "NumMedEnemies": 0,
          "NumHeavyEnemies": 0
        }
      }
    }
  ]
}